twitter_loctagger_it/__init__.py
twitter_loctagger_it/geocoder.py
twitter_loctagger_it/istat.xlsx
twitter_loctagger_it/regions.xlsx
twitter_loctagger_it-0.0.2.dist-info/LICENSE
twitter_loctagger_it-0.0.2.dist-info/METADATA
twitter_loctagger_it-0.0.2.dist-info/WHEEL
twitter_loctagger_it-0.0.2.dist-info/top_level.txt
twitter_loctagger_it-0.0.2.dist-info/RECORD
