Metadata-Version: 2.1
Name: twitter-loctagger-it
Version: 0.0.2
Summary: map Italian Twitter users to a specific city or region in Italy
Home-page: https://github.com/marvin-01/twitter_loctagger_it
Author: Marvin Pappalettera
Author-email: marvinpappalettera99@gmail.com
Classifier: Programming Language :: Python :: 3
Classifier: License :: OSI Approved :: MIT License
Classifier: Operating System :: OS Independent
Requires-Python: >=3.7
License-File: LICENSE
